form_designer/__init__.py
form_designer/admin.py
form_designer/apps.py
form_designer/email.py
form_designer/fields.py
form_designer/forms.py
form_designer/models.py
form_designer/settings.py
form_designer/signals.py
form_designer/uploads.py
form_designer/urls.py
form_designer/utils.py
form_designer/views.py
form_designer/contrib/__init__.py
form_designer/contrib/exporters/__init__.py
form_designer/contrib/exporters/csv_exporter.py
form_designer/contrib/exporters/xls_exporter.py
form_designer/locale/de/LC_MESSAGES/django.po
form_designer/locale/en/LC_MESSAGES/django.po
form_designer/locale/es/LC_MESSAGES/django.po
form_designer/locale/fi/LC_MESSAGES/django.po
form_designer/locale/fr/LC_MESSAGES/django.po
form_designer/locale/nl/LC_MESSAGES/django.po
form_designer/locale/pt_BR/LC_MESSAGES/django.po
form_designer/locale/ru/LC_MESSAGES/django.po
form_designer/locale/sv/LC_MESSAGES/django.po
form_designer/migrations/0001_initial.py
form_designer/migrations/0002_reply_to.py
form_designer/migrations/0003_mail_cover_text.py
form_designer/migrations/__init__.py
form_designer/static/form_designer/js/jquery-inline-collapsible.js
form_designer/static/form_designer/js/jquery-inline-fieldset-collapsible.js
form_designer/static/form_designer/js/jquery-inline-positioning.js
form_designer/static/form_designer/js/jquery-inline-prepopulate-label.js
form_designer/static/form_designer/js/jquery-inline-rename.js
form_designer/static/form_designer/js/jquery-ui.js
form_designer/static/form_designer/js/jquery-url-param.js
form_designer/static/form_designer/js/jquery.js
form_designer/templates/admin/form_designer/formlog/change_list.html
form_designer/templates/html/formdefinition/base.html
form_designer/templates/html/formdefinition/data_message.html
form_designer/templates/html/formdefinition/data_table_message.html
form_designer/templates/html/formdefinition/detail.html
form_designer/templates/html/formdefinition/forms/as_p.html
django_form_designer_ai-2.1.1.1.dist-info/METADATA
django_form_designer_ai-2.1.1.1.dist-info/WHEEL
django_form_designer_ai-2.1.1.1.dist-info/licenses/AUTHORS
django_form_designer_ai-2.1.1.1.dist-info/licenses/LICENSE
django_form_designer_ai-2.1.1.1.dist-info/RECORD
