Metadata-Version: 2.4
Name: django-form-designer-ai
Version: 2.1.1.1
Project-URL: Homepage, https://github.com/andersinno/django-form-designer-ai
License-Expression: BSD-3-Clause
License-File: AUTHORS
License-File: LICENSE
Classifier: Development Status :: 4 - Beta
Classifier: Framework :: Django
Classifier: Intended Audience :: Developers
Classifier: License :: OSI Approved :: BSD License
Classifier: Operating System :: OS Independent
Classifier: Programming Language :: Python
Classifier: Topic :: Internet :: WWW/HTTP
Requires-Python: >=3.8
Requires-Dist: django-picklefield
Requires-Dist: django>=3.0
